karva-0.1.11.dist-info/METADATA
karva-0.1.11.dist-info/WHEEL
karva-0.1.11.dist-info/entry_points.txt
karva-0.1.11.dist-info/licenses/LICENSE
karva/__init__.py
karva/__main__.py
karva/_karva.abi3.so
karva/_karva/__init__.pyi
karva/_karva/tags.pyi
karva/py.typed
karva-0.1.11.dist-info/RECORD
