Metadata-Version: 2.4
Name: karva
Version: 0.1.11
Classifier: License :: OSI Approved :: MIT License
Classifier: Programming Language :: Python
Classifier: Programming Language :: Python :: 3.10
Classifier: Programming Language :: Python :: 3.11
Classifier: Programming Language :: Python :: 3.12
Classifier: Programming Language :: Python :: 3.13
Classifier: Programming Language :: Python :: 3.14
Classifier: Programming Language :: Python :: 3 :: Only
Classifier: Programming Language :: Rust
License-File: LICENSE
Summary: A Python test framework, written in Rust.
Home-Page: https://github.com/MatthewMckee4/karva
Author-email: Matthew McKee <matthewmckee4@yahoo.co.uk>
Requires-Python: >=3.10, <3.15
Project-URL: Documentation, https://matthewmckee4.github.io/karva/
Project-URL: Homepage, https://matthewmckee4.github.io/karva/
Project-URL: Issues, https://github.com/MatthewMckee4/karva/issues
Project-URL: Repository, https://github.com/MatthewMckee4/karva
